deutschland/bundesanzeiger/__init__.py
deutschland/bundesanzeiger/assets/model.onnx
deutschland/bundesanzeiger/bundesanzeiger.py
deutschland/bundesanzeiger/model.py
deutschland/bundesnetzagentur/__init__.py
deutschland/bundesnetzagentur/rufzeichen.py
deutschland/bundeswahlleiter/__init__.py
deutschland/bundeswahlleiter/bundeswahlleiter.py
deutschland/config.py
deutschland/geo.py
deutschland/lebensmittelwarnung/__init__.py
deutschland/lebensmittelwarnung/lebensmittelwarnung.py
deutschland/verena/__init__.py
deutschland/verena/example.md
deutschland/verena/verena.py
deutschland/verena/verenadownloader.py
deutschland/verena/verenaextractor.py
deutschland-0.4.1.dist-info/LICENSE
deutschland-0.4.1.dist-info/METADATA
deutschland-0.4.1.dist-info/WHEEL
deutschland-0.4.1.dist-info/RECORD
