Metadata-Version: 2.1
Name: deutschland
Version: 0.4.1
Summary: 
Home-page: https://github.com/bundesAPI/deutschland
License: Apache-2.0
Author: Lilith Wittmann
Author-email: mail@lilithwittmann.de
Requires-Python: >=3.8,<4
Classifier: License :: OSI Approved :: Apache Software License
Classifier: Programming Language :: Python :: 3
Classifier: Programming Language :: Python :: 3.8
Classifier: Programming Language :: Python :: 3.9
Classifier: Programming Language :: Python :: 3.10
Classifier: Programming Language :: Python :: 3.11
Classifier: Programming Language :: Python :: 3.12
Provides-Extra: abfallnavi
Provides-Extra: all
Provides-Extra: ausbildungssuche
Provides-Extra: berufssprachkurssuche
Provides-Extra: bundeshaushalt
Provides-Extra: bundestag-lobbyregister
Provides-Extra: coachingangebote
Provides-Extra: dashboarddeutschland
Provides-Extra: destatis
Provides-Extra: dip-bundestag
Provides-Extra: ecovisio
Provides-Extra: entgeltatlas
Provides-Extra: feiertage
Provides-Extra: hochwasserzentralen
Provides-Extra: marktstammdaten
Provides-Extra: pegel-online
Provides-Extra: pflanzenschutzmittelzulassung
Provides-Extra: studiensuche
Provides-Extra: tagesschau
Provides-Extra: vag
Provides-Extra: weiterbildungssuche
Requires-Dist: beautifulsoup4 (>=4.9.3,<5.0.0)
Requires-Dist: dateparser (>=1.0.0,<2.0.0)
Requires-Dist: de-abfallnavi (>=0.1.0,<0.2.0) ; extra == "abfallnavi" or extra == "all"
Requires-Dist: de-ausbildungssuche (>=0.1.0,<0.2.0) ; extra == "ausbildungssuche" or extra == "all"
Requires-Dist: de-autobahn (>=1.0.4,<2.0.0)
Requires-Dist: de-berufssprachkurssuche (>=0.1.0,<0.2.0) ; extra == "berufssprachkurssuche" or extra == "all"
Requires-Dist: de-bundeshaushalt (>=1.0.0,<2.0.0) ; extra == "bundeshaushalt" or extra == "all"
Requires-Dist: de-bundesrat (>=0.1.0,<0.2.0)
Requires-Dist: de-bundestag (>=0.1.0,<0.2.0)
Requires-Dist: de-bundestag-lobbyregister (>=0.1.0,<0.2.0) ; extra == "bundestag-lobbyregister" or extra == "all"
Requires-Dist: de-coachingangebote (>=0.1.0,<0.2.0) ; extra == "coachingangebote" or extra == "all"
Requires-Dist: de-dashboarddeutschland (>=0.1.0,<0.2.0) ; extra == "dashboarddeutschland" or extra == "all"
Requires-Dist: de-destatis (>=0.1.0,<0.2.0) ; extra == "destatis" or extra == "all"
Requires-Dist: de-dip-bundestag (>=0.1.0,<0.2.0) ; extra == "dip-bundestag" or extra == "all" or extra == "all"
Requires-Dist: de-dwd (>=1.0.1,<2.0.0)
Requires-Dist: de-ecovisio (>=0.1.0,<0.2.0) ; extra == "ecovisio" or extra == "all"
Requires-Dist: de-entgeltatlas (>=0.1.0,<0.2.0) ; extra == "entgeltatlas" or extra == "all"
Requires-Dist: de-feiertage (>=1.0.1,<2.0.0) ; extra == "feiertage" or extra == "all"
Requires-Dist: de-hochwasserzentralen (>=0.1.0,<0.2.0) ; extra == "hochwasserzentralen" or extra == "all"
Requires-Dist: de-interpol (>=0.1.0,<0.2.0)
Requires-Dist: de-jobsuche (>=0.1.0,<0.2.0)
Requires-Dist: de-ladestationen (>=1.0.5,<2.0.0)
Requires-Dist: de-marktstammdaten (>=0.1.0,<0.2.0) ; extra == "marktstammdaten" or extra == "all"
Requires-Dist: de-mudab (>=0.1.0,<0.2.0)
Requires-Dist: de-nina (>=1.0.1,<2.0.0)
Requires-Dist: de-pegel-online (>=0.1.0,<0.2.0) ; extra == "pegel-online" or extra == "all"
Requires-Dist: de-pflanzenschutzmittelzulassung (>=0.1.0,<0.2.0) ; extra == "pflanzenschutzmittelzulassung" or extra == "all"
Requires-Dist: de-polizei-brandenburg (>=0.1.0,<0.2.0)
Requires-Dist: de-risikogebiete (>=0.1.0,<0.2.0)
Requires-Dist: de-smard (>=0.1.0,<0.2.0)
Requires-Dist: de-strahlenschutz (>=1.0.0,<2.0.0)
Requires-Dist: de-studiensuche (>=0.1.0,<0.2.0) ; extra == "studiensuche" or extra == "all"
Requires-Dist: de-tagesschau (>=0.1.0,<0.2.0) ; extra == "tagesschau" or extra == "all"
Requires-Dist: de-travelwarning (>=0.1.0,<0.2.0)
Requires-Dist: de-vag (>=0.1.0,<0.2.0) ; extra == "vag" or extra == "all"
Requires-Dist: de-weiterbildungssuche (>=0.1.0,<0.2.0) ; extra == "weiterbildungssuche" or extra == "all"
Requires-Dist: de-zoll (>=0.1.0,<0.2.0)
Requires-Dist: lxml (>=4.9.3,<5.0.0)
Requires-Dist: mapbox-vector-tile (>=2.0.1,<3.0.0)
Requires-Dist: more-itertools (>=8.10.0,<9.0.0)
Requires-Dist: numpy (>=1.19.0,<2.0.0) ; python_version >= "3.8" and python_version < "3.12"
Requires-Dist: numpy (>=1.26.2,<2.0.0) ; python_version >= "3.12"
Requires-Dist: onnxruntime (>1.10.0,!=1.16.0)
Requires-Dist: pandas (>2.1.2) ; python_version >= "3.12"
Requires-Dist: pandas ; python_version >= "3.8" and python_version < "3.12"
Requires-Dist: pillow (>=10.0.0,<11.0.0)
Requires-Dist: requests (>=2.26.0,<3.0.0)
Project-URL: Bug Tracker, https://github.com/bundesAPI/deutschland/issues
Project-URL: Repository, https://github.com/bundesAPI/deutschland
